kickstart_iso_tool/__init__.py
kickstart_iso_tool/base.py
kickstart_iso_tool/cli.py
kickstart_iso_tool/constants.py
kickstart_iso_tool/iso.py
kickstart_iso_tool-0.1.1.dist-info/WHEEL
kickstart_iso_tool-0.1.1.dist-info/entry_points.txt
kickstart_iso_tool-0.1.1.dist-info/METADATA
kickstart_iso_tool-0.1.1.dist-info/RECORD
