Metadata-Version: 2.3
Name: kickstart-iso-tool
Version: 0.1.1
Summary: Add your description here
Requires-Dist: jinja2>=3.1.6
Requires-Dist: pycdlib>=1.14.0
Requires-Dist: requests>=2.32.5
Requires-Python: >=3.13
